setup.py
configurations_seddonym/__init__.py
configurations_seddonym/base.py
configurations_seddonym/installations.py
configurations_seddonym/mixins.py
configurations_seddonym/utils.py
django_configurations_seddonym.egg-info/PKG-INFO
django_configurations_seddonym.egg-info/SOURCES.txt
django_configurations_seddonym.egg-info/dependency_links.txt
django_configurations_seddonym.egg-info/top_level.txt