Metadata-Version: 1.0
Name: django-configurations-seddonym
Version: 0.1
Summary: A pack of helpful django-configurations settings for my projects.
Home-page: http://github.com/seddonym/django-configurations-seddonym/
Author: David Seddon
Author-email: david@seddonym.me
License: UNKNOWN
Platform: UNKNOWN
